oliverfarren_python_test_package/__init__.py
oliverfarren_python_test_package/main.py
oliverfarren_python_test_package-0.1.4.dist-info/WHEEL
oliverfarren_python_test_package-0.1.4.dist-info/METADATA
oliverfarren_python_test_package-0.1.4.dist-info/RECORD
