Metadata-Version: 2.1
Name: oliverfarren_python_test_package
Version: 0.1.4
Summary: oliverfarren-python_test_package
Home-page: https://github.com/OliverFarren/oliverfarren-python-test-package
Author: Oliver Farren
Author-email: oliver.farren@gmail.com
Classifier: License :: OSI Approved :: MIT License
